functions_by_stomariv/README.md
functions_by_stomariv/math_functions.py
functions_by_stomariv-0.1.0.dist-info/WHEEL
functions_by_stomariv-0.1.0.dist-info/METADATA
functions_by_stomariv-0.1.0.dist-info/RECORD
